py_trace_log/__init__.py
py_trace_log/trace_log.py
py_trace_log-0.0.1.dist-info/LICENSE
py_trace_log-0.0.1.dist-info/METADATA
py_trace_log-0.0.1.dist-info/WHEEL
py_trace_log-0.0.1.dist-info/top_level.txt
py_trace_log-0.0.1.dist-info/RECORD
